bedfinder/__init__.py
bedfinder/bedfinder.py
bedfinder/filtering.py
bedfinder/utilities.py
bedfinder/models/RandomForest.pkl
bedfinder/models/XGBoost.pkl
bedfinder-0.0.1.dist-info/LICENSE
bedfinder-0.0.1.dist-info/METADATA
bedfinder-0.0.1.dist-info/WHEEL
bedfinder-0.0.1.dist-info/top_level.txt
bedfinder-0.0.1.dist-info/RECORD
