Metadata-Version: 2.1
Name: bedfinder
Version: 0.0.1
Summary: A Python package to automate the classification of glacially derived bedforms.
Author-email: Ellianna Abrahams <ellianna@berkeley.edu>, Marion McKenzie <marion.mckenzie@mines.edu>
Project-URL: Homepage, https://github.com/elliesch/rf_bedform_mapping
Project-URL: Issues, https://github.com/elliesch/rf_bedform_mapping/issues
Classifier: Programming Language :: Python :: 3
Classifier: License :: OSI Approved :: BSD License
Classifier: Operating System :: OS Independent
Classifier: Topic :: Scientific/Engineering :: GIS
Requires-Python: >=3.9
License-File: LICENSE
Requires-Dist: joblib
Requires-Dist: pandas
Requires-Dist: numpy
Requires-Dist: matplotlib
Requires-Dist: scikit-learn ~=1.4.2
Requires-Dist: xgboost ~=2.0.3
